cuteshop/__init__.py
cuteshop/exceptions.py
cuteshop/package.py
cuteshop/run.py
cuteshop/utils.py
cuteshop/downloaders/__init__.py
cuteshop/downloaders/base.py
cuteshop/downloaders/git.py
cuteshop/downloaders/http.py
cuteshop/specs/hoedown.json
cuteshop/specs/libxlsxwriter.yml
cuteshop/specs/libyaml.yml
cuteshop/specs/qcli.yml
cuteshop/specs/qtcollections.yml
cuteshop/specs/qthandlebarsjs.yml
cuteshop/specs/qtsignal.yml
cuteshop/specs/qtyaml.yml
cuteshop/templates/aggregation.pro
cuteshop/templates/common.pri
cuteshop/templates/project.pro
tests/__init__.py
tests/test_cuteshop.py
cuteshop-0.5.0.dist-info/AUTHORS.rst
cuteshop-0.5.0.dist-info/LICENSE
cuteshop-0.5.0.dist-info/METADATA
cuteshop-0.5.0.dist-info/WHEEL
cuteshop-0.5.0.dist-info/entry_points.txt
cuteshop-0.5.0.dist-info/top_level.txt
cuteshop-0.5.0.dist-info/RECORD
