Metadata-Version: 2.1
Name: cuteshop
Version: 0.5.0
Summary: Package manager for Qt projects.
Home-page: https://github.com/uranusjr/cuteshop
Author: Tzu-ping Chung
Author-email: uranusjr@gmail.com
License: MIT
Keywords: cuteshop,qt
Platform: UNKNOWN
Classifier: Development Status :: 2 - Pre-Alpha
Classifier: Intended Audience :: Developers
Classifier: License :: OSI Approved :: MIT License
Classifier: Natural Language :: English
Classifier: Programming Language :: Python :: 2
Classifier: Programming Language :: Python :: 2.7
Classifier: Programming Language :: Python :: 3
Classifier: Programming Language :: Python :: 3.3
Classifier: Programming Language :: Python :: 3.4
Requires-Dist: cached-property
Requires-Dist: jinja2
Requires-Dist: pyyaml
Requires-Dist: setuptools
Requires-Dist: six
Requires-Dist: wheel
